{
  "list": [
    [{
      "id": "84",
      "ico": "https://res-csga.xcydhn.com/5e6c337ef8ca0e494688a398a4e39e88.png",
      "title": "个人中心",
      "url": "开发中...",
      "cate_id": "1"
    }], [{
      "id": "87",
      "ico": "iv_scan",
      "title": "我的二维码",
      "url": "summary://proto?view=MyScanCode_true",
      "cate_id": "2"
    }, {
      "id": "82",
      "ico": "iv_scan_bar",
      "title": "我的条形码",
      "url": "summary://proto?view=MyScanCode_false",
      "cate_id": "2"
    }], [{
      "id": "16",
      "ico": "https:\/\/res-csga.xcydhn.com\/13b9d64f1c3597586adae1104e30f9c8.png",
      "title": "我的任务",
      "url": "colourlife:\/\/proto?type=myPatrolTask",
      "cate_id": "3"
    }, {
      "id": "17",
      "ico": "https:\/\/res-csga.xcydhn.com\/0aed8f6fbf3582fdd3473906740cf65d.png",
      "title": "我的举报",
      "url": "colourlife:\/\/proto?type=myTrack",
      "cate_id": "3"
    }, {
      "id": "18",
      "ico": "https:\/\/res-csga.xcydhn.com\/c24006e00fe20fdd104d6668c57d9260.png",
      "title": "邀请好友",
      "url": "https:\/\/uch5-csga.xcydhn.com\/#\/invitation",
      "cate_id": "3"
    }], [{
      "id": "20",
      "ico": "https:\/\/res-csga.xcydhn.com\/5e6c337ef8ca0e494688a398a4e39e88.png",
      "title": "意见反馈",
      "url": "https:\/\/uch5-csga.xcydhn.com\/#\/sugguest",
      "cate_id": "4"
    }, {
      "id": "74",
      "ico": "https:\/\/res-csga.xcydhn.com\/1ffd4fef00cb246a35df4d286f7b69ae.png",
      "title": "交通事故远程处理志愿者",
      "url": "https:\/\/volunteerv.chehaha.net\/#\/",
      "cate_id": "4"
    }, {
      "id": "19",
      "ico": "https:\/\/res-csga.xcydhn.com\/fab4d4687b5cf4097942c1adc27f9db9.png",
      "title": "设置",
      "url": "colourlife:\/\/proto?type=Setting",
      "cate_id": "4"
    }]
  ]
}